chomper/__init__.py
chomper/arch.py
chomper/const.py
chomper/core.py
chomper/exceptions.py
chomper/log.py
chomper/memory.py
chomper/py.typed
chomper/typing.py
chomper/utils.py
chomper/loader/__init__.py
chomper/loader/base.py
chomper/loader/elf.py
chomper/loader/macho.py
chomper/objc/__init__.py
chomper/objc/block.py
chomper/objc/runtime.py
chomper/objc/types.py
chomper/objc/utils.py
chomper/os/__init__.py
chomper/os/base.py
chomper/os/device.py
chomper/os/android/__init__.py
chomper/os/android/const.py
chomper/os/android/hooks.py
chomper/os/android/os.py
chomper/os/android/structs.py
chomper/os/android/syscall.py
chomper/os/ios/__init__.py
chomper/os/ios/const.py
chomper/os/ios/fixup.py
chomper/os/ios/hooks.py
chomper/os/ios/os.py
chomper/os/ios/structs.py
chomper/os/ios/syscall.py
chomper/os/ios/sysctl.py
chomper-0.3.6.dist-info/licenses/LICENSE
chomper-0.3.6.dist-info/METADATA
chomper-0.3.6.dist-info/WHEEL
chomper-0.3.6.dist-info/top_level.txt
chomper-0.3.6.dist-info/RECORD
