Metadata-Version: 2.4
Name: chomper
Version: 0.3.6
Summary: A lightweight emulation framework for emulating security algorithms of iOS executables and libraries.
Author-email: Sh4w <sledgeh4w@gmail.com>
License: MIT
Classifier: License :: OSI Approved :: MIT License
Classifier: Operating System :: OS Independent
Classifier: Programming Language :: Python :: 3 :: Only
Classifier: Programming Language :: Python :: 3.8
Classifier: Programming Language :: Python :: 3.9
Classifier: Programming Language :: Python :: 3.10
Classifier: Programming Language :: Python :: 3.11
Classifier: Programming Language :: Python :: 3.12
Classifier: Programming Language :: Python :: 3.13
Classifier: Programming Language :: Python :: 3.14
Requires-Python: >=3.8
License-File: LICENSE
Requires-Dist: pyelftools>=0.29
Requires-Dist: unicorn>=2.0.0
Requires-Dist: capstone>=5.0.0.post1
Requires-Dist: lief>=0.16.0
Dynamic: license-file
